RiboMetric/RiboMetric.py
RiboMetric/SRR618774_RiboMetric.csv
RiboMetric/SRR618774_RiboMetric.html
RiboMetric/SRR618774_RiboMetric.json
RiboMetric/SRR618774_RiboMetric.pdf
RiboMetric/__init__.py
RiboMetric/arg_parser.py
RiboMetric/bam_processing.py
RiboMetric/bam_splitting.py
RiboMetric/cli.py
RiboMetric/config.yml
RiboMetric/file_parser.py
RiboMetric/file_splitting.py
RiboMetric/html_report.py
RiboMetric/json_output.py
RiboMetric/metrics.py
RiboMetric/modules.py
RiboMetric/plots.py
RiboMetric/qc.py
RiboMetric/results_output.py
RiboMetric/templates/RiboMetric_favicon.png
RiboMetric/templates/RiboMetric_logo.png
RiboMetric/templates/base.html
RiboMetric-0.1.12.dist-info/AUTHORS.rst
RiboMetric-0.1.12.dist-info/LICENSE
RiboMetric-0.1.12.dist-info/METADATA
RiboMetric-0.1.12.dist-info/WHEEL
RiboMetric-0.1.12.dist-info/entry_points.txt
RiboMetric-0.1.12.dist-info/top_level.txt
RiboMetric-0.1.12.dist-info/RECORD
